finlay/__init__.py
finlay/core.py
finlay-0.1.9.dist-info/LICENSE.txt
finlay-0.1.9.dist-info/METADATA
finlay-0.1.9.dist-info/WHEEL
finlay-0.1.9.dist-info/top_level.txt
finlay-0.1.9.dist-info/RECORD
