Metadata-Version: 2.1
Name: finlay
Version: 0.1.9
Summary: A Toy Experiment to 
Home-page: https://github.com/sabbiramin113008/finlay
Author: Sabbir Amin
Author-email: sabbiramin.cse11ruet@gmail.com
License: MIT
Platform: UNKNOWN
Classifier: License :: OSI Approved :: MIT License
Classifier: Programming Language :: Python
Classifier: Operating System :: OS Independent
Classifier: Topic :: Utilities
